cyborgdb_service/__init__.py
cyborgdb_service/__main__.py
cyborgdb_service/app.py
cyborgdb_service/main.py
cyborgdb_service/package_installer.py
cyborgdb_service/api/__init__.py
cyborgdb_service/api/deps.py
cyborgdb_service/api/routes/__init__.py
cyborgdb_service/api/routes/health.py
cyborgdb_service/api/routes/indexes.py
cyborgdb_service/api/routes/vectors.py
cyborgdb_service/api/schemas/__init__.py
cyborgdb_service/api/schemas/index.py
cyborgdb_service/api/schemas/vectors.py
cyborgdb_service/core/__init__.py
cyborgdb_service/core/config.py
cyborgdb_service/core/security.py
cyborgdb_service/core/training_lock.py
cyborgdb_service/core/training_manager.py
cyborgdb_service/db/__init__.py
cyborgdb_service/db/client.py
cyborgdb_service/utils/__init__.py
cyborgdb_service/utils/endpoints.py
cyborgdb_service/utils/environment_check.py
cyborgdb_service/utils/error_handler.py
cyborgdb_service-0.12.0.dist-info/licenses/LICENSE
cyborgdb_service-0.12.0.dist-info/METADATA
cyborgdb_service-0.12.0.dist-info/WHEEL
cyborgdb_service-0.12.0.dist-info/entry_points.txt
cyborgdb_service-0.12.0.dist-info/top_level.txt
cyborgdb_service-0.12.0.dist-info/RECORD
